{
    "target_audience": "Software startups marketing directors",
    "industry": "Tech, Software",
    "region": "Germany",
    "company_size": "Startup (1-11 employees)",
    "role_keywords": [
        "CMO",
        "Managing Directors"
    ],
    "goal_intent": "Book Demo Calls",
    "about_yourself": "With Droidrun you can automate any mobile app. Grant AI native control of virtual & physical phones - Automate mobile workflows, unlock data, and more. Everything is possible through natural language."
}